aruco_estimator/__init__.py
aruco_estimator/aruco.py
aruco_estimator/cli.py
aruco_estimator/opt.py
aruco_estimator/utils.py
aruco_estimator/visualization.py
aruco_estimator/sfm/colmap.py
aruco_estimator/sfm/common.py
aruco_estimator/tools/README.md
aruco_estimator/tools/register.py
aruco_estimator-1.2.0.dist-info/METADATA
aruco_estimator-1.2.0.dist-info/WHEEL
aruco_estimator-1.2.0.dist-info/entry_points.txt
aruco_estimator-1.2.0.dist-info/licenses/LICENSE
aruco_estimator-1.2.0.dist-info/RECORD
