Metadata-Version: 2.4
Name: aruco-estimator
Version: 1.2.0
Summary: Scene pose estimation using ArUco markers and 3D point clouds.
Author-email: Lukas Meyer <lukas.meyer@fau.de>, Nile Walker <nilezwalker@gmail.com>
License-File: LICENSE
Requires-Python: <4.0,>=3.9
Requires-Dist: click<9,>=8.1.8
Requires-Dist: numpy>=1.22.4
Requires-Dist: open3d<0.20,>=0.19.0
Requires-Dist: opencv-contrib-python>=4.10.0.84
Requires-Dist: opencv-python>=4.10.0.84
Requires-Dist: pyquaternion==0.9.9
Requires-Dist: pyransac3d==0.6.0
Requires-Dist: scikit-learn>=1.3.2
Requires-Dist: tqdm>=4.64.0
